AChemKit.pdf
MANIFEST.in
README.txt
setup.py
AChemKit/__init__.py
AChemKit/bucket.py
AChemKit/properties.py
AChemKit/properties_motif.py
AChemKit/properties_wnx.py
AChemKit/randomnet.py
AChemKit/randomnet_test.py
AChemKit/reactionnet.py
AChemKit/reactionnet_test.py
AChemKit/reactionnetdot.py
AChemKit/reactionnetdot_test.py
AChemKit/sims_gillespie.py
AChemKit/sims_gillespie_test.py
AChemKit/sims_simple.py
AChemKit/sims_simple_test.py
AChemKit.egg-info/PKG-INFO
AChemKit.egg-info/SOURCES.txt
AChemKit.egg-info/dependency_links.txt
AChemKit.egg-info/top_level.txt
AChemKit/tools/__init__.py
AChemKit/tools/chem_linear.py
AChemKit/tools/chem_pp.py
AChemKit/tools/chem_to_dot.py
AChemKit/tools/chem_to_pdf.py
AChemKit/tools/chem_uniform.py
AChemKit/tools/log_to_chem.py
AChemKit/utils/__init__.py
AChemKit/utils/bag.py
AChemKit/utils/bag_test.py
AChemKit/utils/simpledot.py
AChemKit/utils/utils.py
AChemKit/utils/utils_test.py
doc/html/AChemKit.html
doc/html/AChemKit.properties.html
doc/html/AChemKit.randomnet.Linear.html
doc/html/AChemKit.randomnet.Uniform.html
doc/html/AChemKit.randomnet.html
doc/html/AChemKit.reactionnet.html
doc/html/AChemKit.tools.chem_pp.html
doc/html/AChemKit.tools.chem_to_dot.html
doc/html/AChemKit.tools.chem_to_pdf.html
doc/html/AChemKit.tools.html
doc/html/AChemKit.utils.html
doc/html/AChemKit.utils.simpledot.html
doc/html/README.html
doc/html/TODO.html
doc/html/autoAChemKit.html
doc/html/fileformats.html
doc/html/genindex.html
doc/html/index.html
doc/html/modules.html
doc/html/objects.inv
doc/html/py-modindex.html
doc/html/search.html
doc/html/searchindex.js
doc/html/_static/basic.css
doc/html/_static/default.css
doc/html/_static/doctools.js
doc/html/_static/file.png
doc/html/_static/jquery.js
doc/html/_static/minus.png
doc/html/_static/plus.png
doc/html/_static/pygments.css
doc/html/_static/searchtools.js
doc/html/_static/sidebar.js
doc/html/_static/underscore.js
doc/html/docs/AChemKit.html
doc/html/docs/AChemKit.properties.html
doc/html/docs/AChemKit.randomnet.html
doc/html/docs/AChemKit.reactionnet.html
doc/html/docs/AChemKit.tools.chem_pp.html
