Metadata-Version: 1.0
Name: AChemKit
Version: 0.3.0
Summary: An Artificial Chemistry Tookit
Home-page: https://github.com/afaulconbridge/PyAChemKit
Author: Adam Faulconbridge
Author-email: afaulconbridge@googlemail.com
License: UNKNOWN
Download-URL: http://pypi.python.org/packages/source/A/AChemKit/AChemKit-0.1.0.tar.gz#md5=a4b09ccb7ce61642305e3ef5874ac924
Platform: UNKNOWN
Classifier: Development Status :: 3 - Alpha
Classifier: Intended Audience :: Science/Research
Classifier: Intended Audience :: Developers
Classifier: License :: OSI Approved :: BSD License
Classifier: Natural Language :: English
Classifier: Operating System :: OS Independent
Classifier: Programming Language :: Python
Classifier: Programming Language :: Python :: 2.6
Classifier: Programming Language :: Python :: 2.7
Classifier: Topic :: Scientific/Engineering :: Artificial Life
Classifier: Topic :: Scientific/Engineering :: Chemistry
Classifier: Topic :: Software Development :: Libraries :: Python Modules
